{"list":[{"accountid":0,"accountname":"","cjsj":"2021-08-25","cqmc":"西湖区","cqsj":0,"cyrybh":"","czfs":0,"dqlc":"","fbzt":1,"fczsh":"浙(2020)杭州市不动产权第0230553号","fwcode":0,"fwtybh":"210825PS389196","fwyt":0,"fwytValue":"","gisx":"","gisy":"","gpfyid":3523891,"gpfyxzqh":0,"gphytgsj":"","gpid":439087568,"gplxfs":"","gplxrcode":0,"gplxrdh":"","gplxrxm":"陈玲玲","gply":0,"gpzt":3,"gpztValue":"挂牌成功","hxs":0,"hxt":0,"hxw":0,"hyid":0,"hyjzsj":"","isnew":0,"jmlx":0,"jmqymc":"","jzmj":88.34,"lsbz":0,"mdmc":"杭州新语房地产经纪有限公司","qycode":0,"qyid":0,"qyzt":0,"scgpshsj":"2021-08-26","sellnum":0,"sffzjg":0,"sjhm":"","sqhysj":"","szlc":"","szlcname":"","tjsum":0,"tygpbh":"35238913325","wtcsjg":525,"wtdqts":0,"wtxybh":"2021082510597567","wtxycode":0,"wtxyid":0,"xqid":0,"xqmc":"盛世诚品公寓","xzqh":33,"xzqhname":"西湖区","zzcs":""},{"accountid":0,"accountname":"","cjsj":"2021-08-26","cqmc":"西湖区","cqsj":0,"cyrybh":"","czfs":0,"dqlc":"","fbzt":1,"fczsh":"杭房权证西移字第07524703号","fwcode":0,"fwtybh":"210826HW514744","fwyt":0,"fwytValue":"","gisx":"","gisy":"","gpfyid":3525147,"gpfyxzqh":0,"gphytgsj":"","gpid":439382946,"gplxfs":"","gplxrcode":0,"gplxrdh":"","gplxrxm":"赵冬梅","gply":0,"gpzt":3,"gpztValue":"挂牌成功","hxs":0,"hxt":0,"hxw":0,"hyid":0,"hyjzsj":"","isnew":0,"jmlx":0,"jmqymc":"","jzmj":131.25,"lsbz":0,"mdmc":"杭州我爱我家房地产经纪有限公司保俶路分公司","qycode":0,"qyid":0,"qyzt":0,"scgpshsj":"2021-08-26","sellnum":0,"sffzjg":0,"sjhm":"","sqhysj":"","szlc":"","szlcname":"","tjsum":0,"tygpbh":"35251475806","wtcsjg":1200,"wtdqts":0,"wtxybh":"2021082609002945","wtxycode":0,"wtxyid":0,"xqid":0,"xqmc":"晴园","xzqh":33,"xzqhname":"西湖区","zzcs":""},{"accountid":0,"accountname":"","cjsj":"2021-08-25","cqmc":"西湖区","cqsj":0,"cyrybh":"","czfs":0,"dqlc":"","fbzt":1,"fczsh":"杭房权证西移字第16265606号","fwcode":0,"fwtybh":"201020TY867487","fwyt":0,"fwytValue":"","gisx":"","gisy":"","gpfyid":3524456,"gpfyxzqh":0,"gphytgsj":"","gpid":439201310,"gplxfs":"","gplxrcode":0,"gplxrdh":"","gplxrxm":"虞伟","gply":0,"gpzt":3,"gpztValue":"挂牌成功","hxs":0,"hxt":0,"hxw":0,"hyid":0,"hyjzsj":"","isnew":0,"jmlx":0,"jmqymc":"","jzmj":63.48,"lsbz":0,"mdmc":"杭州怀瑾房地产营销策划有限公司","qycode":0,"qyid":0,"qyzt":0,"scgpshsj":"2021-08-26","sellnum":0,"sffzjg":0,"sjhm":"","sqhysj":"","szlc":"","szlcname":"","tjsum":0,"tygpbh":"35244568178","wtcsjg":312,"wtdqts":0,"wtxybh":"2021082503211309","wtxycode":0,"wtxyid":0,"xqid":0,"xqmc":"留下西苑","xzqh":33,"xzqhname":"西湖区","zzcs":""},{"accountid":0,"accountname":"","cjsj":"2021-08-25","cqmc":"西湖区","cqsj":0,"cyrybh":"","czfs":0,"dqlc":"","fbzt":1,"fczsh":"浙(2021)杭州市不动产权第0239128号","fwcode":0,"fwtybh":"210825HD496910","fwyt":0,"fwytValue":"","gisx":"","gisy":"","gpfyid":3525081,"gpfyxzqh":0,"gphytgsj":"","gpid":439299450,"gplxfs":"","gplxrcode":0,"gplxrdh":"","gplxrxm":"王菊","gply":0,"gpzt":3,"gpztValue":"挂牌成功","hxs":0,"hxt":0,"hxw":0,"hyid":0,"hyjzsj":"","isnew":0,"jmlx":0,"jmqymc":"","jzmj":66.21,"lsbz":0,"mdmc":"杭州我爱我家房地产经纪有限公司保俶路分公司","qycode":0,"qyid":0,"qyzt":0,"scgpshsj":"2021-08-26","sellnum":0,"sffzjg":0,"sjhm":"","sqhysj":"","szlc":"","szlcname":"","tjsum":0,"tygpbh":"35250811497","wtcsjg":200,"wtdqts":0,"wtxybh":"2021082510129449","wtxycode":0,"wtxyid":0,"xqid":0,"xqmc":"德泽家园","xzqh":33,"xzqhname":"西湖区","zzcs":""},{"accountid":0,"accountname":"","cjsj":"2021-08-22","cqmc":"西湖区","cqsj":0,"cyrybh":"","czfs":0,"dqlc":"","fbzt":1,"fczsh":"杭房权证西移字第15964560号","fwcode":0,"fwtybh":"210822ZB829111","fwyt":0,"fwytValue":"","gisx":"","gisy":"","gpfyid":3518291,"gpfyxzqh":0,"gphytgsj":"","gpid":437761823,"gplxfs":"","gplxrcode":0,"gplxrdh":"","gplxrxm":"包珊珊","gply":0,"gpzt":3,"gpztValue":"挂牌成功","hxs":0,"hxt":0,"hxw":0,"hyid":0,"hyjzsj":"","isnew":0,"jmlx":0,"jmqymc":"","jzmj":251.24,"lsbz":0,"mdmc":"杭州一可房产咨询有限公司","qycode":0,"qyid":0,"qyzt":0,"scgpshsj":"2021-08-26","sellnum":0,"sffzjg":0,"sjhm":"","sqhysj":"","szlc":"","szlcname":"","tjsum":0,"tygpbh":"35182914666","wtcsjg":1750,"wtdqts":0,"wtxybh":"2021082211521822","wtxycode":0,"wtxyid":0,"xqid":0,"xqmc":"香溪公寓","xzqh":33,"xzqhname":"西湖区","zzcs":""},{"accountid":0,"accountname":"","cjsj":"2021-08-25","cqmc":"西湖区","cqsj":0,"cyrybh":"","czfs":0,"dqlc":"","fbzt":1,"fczsh":"浙(2016)杭州市不动产权第0036118号","fwcode":0,"fwtybh":"180926085063","fwyt":0,"fwytValue":"","gisx":"","gisy":"","gpfyid":3525030,"gpfyxzqh":0,"gphytgsj":"","gpid":439283359,"gplxfs":"","gplxrcode":0,"gplxrdh":"","gplxrxm":"林余凤","gply":0,"gpzt":3,"gpztValue":"挂牌成功","hxs":0,"hxt":0,"hxw":0,"hyid":0,"hyjzsj":"","isnew":0,"jmlx":0,"jmqymc":"","jzmj":56.88,"lsbz":0,"mdmc":"杭州我爱我家房地产经纪有限公司保俶路分公司","qycode":0,"qyid":0,"qyzt":0,"scgpshsj":"2021-08-26","sellnum":0,"sffzjg":0,"sjhm":"","sqhysj":"","szlc":"","szlcname":"","tjsum":0,"tygpbh":"35250305897","wtcsjg":300,"wtdqts":0,"wtxybh":"2021082508333358","wtxycode":0,"wtxyid":0,"xqid":0,"xqmc":"九莲新村","xzqh":33,"xzqhname":"西湖区","zzcs":""},{"accountid":0,"accountname":"","cjsj":"2021-08-25","cqmc":"西湖区","cqsj":0,"cyrybh":"","czfs":0,"dqlc":"","fbzt":1,"fczsh":"浙(2017)杭州市不动产权第0297812号","fwcode":0,"fwtybh":"210512BS451695","fwyt":0,"fwytValue":"","gisx":"","gisy":"","gpfyid":3524997,"gpfyxzqh":0,"gphytgsj":"","gpid":439281775,"gplxfs":"","gplxrcode":0,"gplxrdh":"","gplxrxm":"刘涛","gply":0,"gpzt":3,"gpztValue":"挂牌成功","hxs":0,"hxt":0,"hxw":0,"hyid":0,"hyjzsj":"","isnew":0,"jmlx":0,"jmqymc":"","jzmj":141.85,"lsbz":0,"mdmc":"浙江绿城房屋置换有限公司杭州慧园店","qycode":0,"qyid":0,"qyzt":0,"scgpshsj":"2021-08-26","sellnum":0,"sffzjg":0,"sjhm":"","sqhysj":"","szlc":"","szlcname":"","tjsum":0,"tygpbh":"35249974202","wtcsjg":960,"wtdqts":0,"wtxybh":"2021082508031774","wtxycode":0,"wtxyid":0,"xqid":0,"xqmc":"华海园","xzqh":33,"xzqhname":"西湖区","zzcs":""},{"accountid":0,"accountname":"","cjsj":"2021-08-22","cqmc":"西湖区","cqsj":0,"cyrybh":"","czfs":0,"dqlc":"","fbzt":1,"fczsh":"浙(2017)杭州市不动产权第0075736号","fwcode":0,"fwtybh":"210822ZW791642","fwyt":0,"fwytValue":"","gisx":"","gisy":"","gpfyid":3517916,"gpfyxzqh":0,"gphytgsj":"","gpid":437680812,"gplxfs":"","gplxrcode":0,"gplxrdh":"","gplxrxm":"赵庆宇","gply":0,"gpzt":3,"gpztValue":"挂牌成功","hxs":0,"hxt":0,"hxw":0,"hyid":0,"hyjzsj":"","isnew":0,"jmlx":0,"jmqymc":"","jzmj":79.98,"lsbz":0,"mdmc":"浙江链家房地产经纪有限公司杭州文二路五店","qycode":0,"qyid":0,"qyzt":0,"scgpshsj":"2021-08-26","sellnum":0,"sffzjg":0,"sjhm":"","sqhysj":"","szlc":"","szlcname":"","tjsum":0,"tygpbh":"35179164412","wtcsjg":630,"wtdqts":0,"wtxybh":"2021082210270811","wtxycode":0,"wtxyid":0,"xqid":0,"xqmc":"师苑新村","xzqh":33,"xzqhname":"西湖区","zzcs":""},{"accountid":0,"accountname":"","cjsj":"2021-08-25","cqmc":"西湖区","cqsj":0,"cyrybh":"","czfs":0,"dqlc":"","fbzt":1,"fczsh":"杭房权证拱移字第15117612号","fwcode":0,"fwtybh":"200726BC679262","fwyt":0,"fwytValue":"","gisx":"","gisy":"","gpfyid":3524865,"gpfyxzqh":0,"gphytgsj":"","gpid":439260523,"gplxfs":"","gplxrcode":0,"gplxrdh":"","gplxrxm":"张启宝","gply":0,"gpzt":3,"gpztValue":"挂牌成功","hxs":0,"hxt":0,"hxw":0,"hyid":0,"hyjzsj":"","isnew":0,"jmlx":0,"jmqymc":"","jzmj":76.45,"lsbz":0,"mdmc":"杭州我爱我家房地产经纪有限公司保俶路分公司","qycode":0,"qyid":0,"qyzt":0,"scgpshsj":"2021-08-26","sellnum":0,"sffzjg":0,"sjhm":"","sqhysj":"","szlc":"","szlcname":"","tjsum":0,"tygpbh":"35248653934","wtcsjg":310,"wtdqts":0,"wtxybh":"2021082506330522","wtxycode":0,"wtxyid":0,"xqid":0,"xqmc":"庆隆苑","xzqh":33,"xzqhname":"西湖区","zzcs":""},{"accountid":0,"accountname":"","cjsj":"2021-08-25","cqmc":"西湖区","cqsj":0,"cyrybh":"","czfs":0,"dqlc":"","fbzt":1,"fczsh":"浙(2016)杭州市不动产权第0071148号","fwcode":0,"fwtybh":"191028411344","fwyt":0,"fwytValue":"","gisx":"","gisy":"","gpfyid":3524870,"gpfyxzqh":0,"gphytgsj":"","gpid":439265353,"gplxfs":"","gplxrcode":0,"gplxrdh":"","gplxrxm":"钟秋亚","gply":0,"gpzt":3,"gpztValue":"挂牌成功","hxs":0,"hxt":0,"hxw":0,"hyid":0,"hyjzsj":"","isnew":0,"jmlx":0,"jmqymc":"","jzmj":129.65,"lsbz":0,"mdmc":"浙江绿城房屋置换有限公司杭州梧桐公寓店","qycode":0,"qyid":0,"qyzt":0,"scgpshsj":"2021-08-26","sellnum":0,"sffzjg":0,"sjhm":"","sqhysj":"","szlc":"","szlcname":"","tjsum":0,"tygpbh":"35248707242","wtcsjg":860,"wtdqts":0,"wtxybh":"2021082506425352","wtxycode":0,"wtxyid":0,"xqid":0,"xqmc":"桂花城","xzqh":33,"xzqhname":"西湖区","zzcs":""}],"totaltows":22776,"pageinfo":"<a href=\"javascript:void(0);\" class=\"c\" onclick=\"doPage(1);return false;\">首页</a><a href=\"javascript:void(0);\" class=\"c\" onclick=\"doPage(1230);return false;\">上一页</a><a href=\"javascript:void(0);\" onclick=\"doPage(1229);return false;\" class=\"c\" >1229</a><a href=\"javascript:void(0);\" onclick=\"doPage(1230);return false;\" class=\"c\" >1230</a><a href=\"javascript:void(0);\" onclick=\"doPage(1231);return false;\" class=\"d\" >1231</a><a href=\"javascript:void(0);\" onclick=\"doPage(1232);return false;\" class=\"c\" >1232</a><a href=\"javascript:void(0);\" onclick=\"doPage(1233);return false;\" class=\"c\" >1233</a><a href=\"javascript:void(0)\" class=\"c\" onclick=\"doPage(1232);return false;\">下一页</a><a href=\"javascript:void(0)\" class=\"c\" onclick=\"doPage(2278);return false;\">尾页</a><span class=\"nlc_totalpage\">共 <font class=\"color-blue09\">2278</font> 页 第<input type=\"text\" value=\"1231\" name=\"_page\" id=\"_page\" onkeydown=\"javascript:if(event.keyCode==13)doPage($('#_page').val());\">页 <a href=\"javaScript:doPage($('#_page').val());\">确定</a></span><br/>(共22776条)"}