{"list":[{"accountid":0,"accountname":"","cjsj":"2022-07-03","cqmc":"西湖区","cqsj":0,"cyrybh":"","czfs":0,"dqlc":"","fbzt":1,"fczsh":"杭房权证西移字第12052300号","fwcode":0,"fwtybh":"220703LG249751","fwyt":0,"fwytValue":"","gisx":"","gisy":"","gpfyid":3822497,"gpfyxzqh":0,"gphytgsj":"","gpid":570714657,"gplxfs":"","gplxrcode":0,"gplxrdh":"","gplxrxm":"童超","gply":0,"gpzt":3,"gpztValue":"挂牌成功","hxs":0,"hxt":0,"hxw":0,"hyid":0,"hyjzsj":"","isnew":0,"jmlx":0,"jmqymc":"","jzmj":65.11,"lsbz":0,"mdmc":"浙江链家房地产经纪有限公司杭州杨梅山路店","qycode":0,"qyid":0,"qyzt":0,"scgpshsj":"2022-07-05","sellnum":0,"sffzjg":0,"sjhm":"","sqhysj":"","szlc":"","szlcname":"","tjsum":0,"tygpbh":"38224974598","wtcsjg":250,"wtdqts":0,"wtxybh":"2022070311344656","wtxycode":0,"wtxyid":0,"xqid":0,"xqmc":"和家园","xzqh":33,"xzqhname":"西湖区","zzcs":""},{"accountid":0,"accountname":"","cjsj":"2022-07-04","cqmc":"西湖区","cqsj":0,"cyrybh":"","czfs":0,"dqlc":"","fbzt":1,"fczsh":"杭房权证西移字第0066757号","fwcode":0,"fwtybh":"220704MK418655","fwyt":0,"fwytValue":"","gisx":"","gisy":"","gpfyid":3824186,"gpfyxzqh":0,"gphytgsj":"","gpid":571264918,"gplxfs":"","gplxrcode":0,"gplxrdh":"","gplxrxm":"廖樟聪","gply":0,"gpzt":3,"gpztValue":"挂牌成功","hxs":0,"hxt":0,"hxw":0,"hyid":0,"hyjzsj":"","isnew":0,"jmlx":0,"jmqymc":"","jzmj":106.47,"lsbz":0,"mdmc":"杭州成又房地产经纪有限公司西湖分公司","qycode":0,"qyid":0,"qyzt":0,"scgpshsj":"2022-07-05","sellnum":0,"sffzjg":0,"sjhm":"","sqhysj":"","szlc":"","szlcname":"","tjsum":0,"tygpbh":"38241867684","wtcsjg":450,"wtdqts":0,"wtxybh":"2022070405364917","wtxycode":0,"wtxyid":0,"xqid":0,"xqmc":"香港城","xzqh":33,"xzqhname":"西湖区","zzcs":""},{"accountid":0,"accountname":"","cjsj":"2022-07-04","cqmc":"西湖区","cqsj":0,"cyrybh":"","czfs":0,"dqlc":"","fbzt":1,"fczsh":"浙(2022)杭州市不动产权第0087966号","fwcode":0,"fwtybh":"220508VX222510","fwyt":0,"fwytValue":"","gisx":"","gisy":"","gpfyid":3824048,"gpfyxzqh":0,"gphytgsj":"","gpid":571221095,"gplxfs":"","gplxrcode":0,"gplxrdh":"","gplxrxm":"陈春容","gply":0,"gpzt":3,"gpztValue":"挂牌成功","hxs":0,"hxt":0,"hxw":0,"hyid":0,"hyjzsj":"","isnew":0,"jmlx":0,"jmqymc":"","jzmj":61.09,"lsbz":0,"mdmc":"杭州豪世华邦润达房地产代理有限公司","qycode":0,"qyid":0,"qyzt":0,"scgpshsj":"2022-07-05","sellnum":0,"sffzjg":0,"sjhm":"","sqhysj":"","szlc":"","szlcname":"","tjsum":0,"tygpbh":"38240489602","wtcsjg":200,"wtdqts":0,"wtxybh":"2022070403591094","wtxycode":0,"wtxyid":0,"xqid":0,"xqmc":"都市阳光华苑","xzqh":33,"xzqhname":"西湖区","zzcs":""},{"accountid":0,"accountname":"","cjsj":"2022-06-27","cqmc":"西湖区","cqsj":0,"cyrybh":"","czfs":0,"dqlc":"","fbzt":1,"fczsh":"杭房权证西改字第0144469号","fwcode":0,"fwtybh":"220627AE399110","fwyt":0,"fwytValue":"","gisx":"","gisy":"","gpfyid":3813991,"gpfyxzqh":0,"gphytgsj":"","gpid":567658947,"gplxfs":"","gplxrcode":0,"gplxrdh":"","gplxrxm":"王玉坤","gply":0,"gpzt":3,"gpztValue":"挂牌成功","hxs":0,"hxt":0,"hxw":0,"hyid":0,"hyjzsj":"","isnew":0,"jmlx":0,"jmqymc":"","jzmj":87.15,"lsbz":0,"mdmc":"杭州成又房地产经纪有限公司西湖分公司","qycode":0,"qyid":0,"qyzt":0,"scgpshsj":"2022-07-05","sellnum":0,"sffzjg":0,"sjhm":"","sqhysj":"","szlc":"","szlcname":"","tjsum":0,"tygpbh":"38139913572","wtcsjg":396,"wtdqts":0,"wtxybh":"2022062708108946","wtxycode":0,"wtxyid":0,"xqid":0,"xqmc":"美都公寓","xzqh":33,"xzqhname":"西湖区","zzcs":""},{"accountid":0,"accountname":"","cjsj":"2022-05-19","cqmc":"西湖区","cqsj":0,"cyrybh":"","czfs":0,"dqlc":"","fbzt":1,"fczsh":"浙(2019)杭州市不动产权第0167657号","fwcode":0,"fwtybh":"220519TA429890","fwyt":0,"fwytValue":"","gisx":"","gisy":"","gpfyid":3764382,"gpfyxzqh":0,"gphytgsj":"","gpid":550111051,"gplxfs":"","gplxrcode":0,"gplxrdh":"","gplxrxm":"沈龙飞","gply":0,"gpzt":3,"gpztValue":"挂牌成功","hxs":0,"hxt":0,"hxw":0,"hyid":0,"hyjzsj":"","isnew":0,"jmlx":0,"jmqymc":"","jzmj":122.03,"lsbz":0,"mdmc":"杭州我爱我家房地产经纪有限公司香积寺路分公司","qycode":0,"qyid":0,"qyzt":0,"scgpshsj":"2022-07-05","sellnum":0,"sffzjg":0,"sjhm":"","sqhysj":"","szlc":"","szlcname":"","tjsum":0,"tygpbh":"37643824538","wtcsjg":460,"wtdqts":0,"wtxybh":"2022051904331050","wtxycode":0,"wtxyid":0,"xqid":0,"xqmc":"同仁家园","xzqh":33,"xzqhname":"西湖区","zzcs":""},{"accountid":0,"accountname":"","cjsj":"2022-07-03","cqmc":"西湖区","cqsj":0,"cyrybh":"","czfs":0,"dqlc":"","fbzt":1,"fczsh":"浙(2018)杭州市不动产权第0166661号","fwcode":0,"fwtybh":"220703AB210070","fwyt":0,"fwytValue":"","gisx":"","gisy":"","gpfyid":3822100,"gpfyxzqh":0,"gphytgsj":"","gpid":570649377,"gplxfs":"","gplxrcode":0,"gplxrdh":"","gplxrxm":"苏志敏","gply":0,"gpzt":3,"gpztValue":"挂牌成功","hxs":0,"hxt":0,"hxw":0,"hyid":0,"hyjzsj":"","isnew":0,"jmlx":0,"jmqymc":"","jzmj":88.81,"lsbz":0,"mdmc":"杭州我爱我家房地产经纪有限公司转塘第一分公司","qycode":0,"qyid":0,"qyzt":0,"scgpshsj":"2022-07-05","sellnum":0,"sffzjg":0,"sjhm":"","sqhysj":"","szlc":"","szlcname":"","tjsum":0,"tygpbh":"38221008904","wtcsjg":285,"wtdqts":0,"wtxybh":"2022070308019376","wtxycode":0,"wtxyid":0,"xqid":0,"xqmc":"康新花园","xzqh":33,"xzqhname":"西湖区","zzcs":""},{"accountid":0,"accountname":"","cjsj":"2022-07-04","cqmc":"西湖区","cqsj":0,"cyrybh":"","czfs":0,"dqlc":"","fbzt":1,"fczsh":"浙(2018)杭州市不动产权第0024276号","fwcode":0,"fwtybh":"220704MW398360","fwyt":0,"fwytValue":"","gisx":"","gisy":"","gpfyid":3823983,"gpfyxzqh":0,"gphytgsj":"","gpid":571206762,"gplxfs":"","gplxrcode":0,"gplxrdh":"","gplxrxm":"肖杨杨","gply":0,"gpzt":3,"gpztValue":"挂牌成功","hxs":0,"hxt":0,"hxw":0,"hyid":0,"hyjzsj":"","isnew":0,"jmlx":0,"jmqymc":"","jzmj":89.68,"lsbz":0,"mdmc":"杭州我爱我家房地产经纪有限公司保俶路分公司","qycode":0,"qyid":0,"qyzt":0,"scgpshsj":"2022-07-05","sellnum":0,"sffzjg":0,"sjhm":"","sqhysj":"","szlc":"","szlcname":"","tjsum":0,"tygpbh":"38239836763","wtcsjg":765,"wtdqts":0,"wtxybh":"2022070403156761","wtxycode":0,"wtxyid":0,"xqid":0,"xqmc":"西溪河滨之城","xzqh":33,"xzqhname":"西湖区","zzcs":""},{"accountid":0,"accountname":"","cjsj":"2022-06-22","cqmc":"西湖区","cqsj":0,"cyrybh":"","czfs":0,"dqlc":"","fbzt":1,"fczsh":"杭房权证西移字第12125981号","fwcode":0,"fwtybh":"220622IA860443","fwyt":0,"fwytValue":"","gisx":"","gisy":"","gpfyid":3808714,"gpfyxzqh":0,"gphytgsj":"","gpid":565374953,"gplxfs":"","gplxrcode":0,"gplxrdh":"","gplxrxm":"李昱楼","gply":0,"gpzt":3,"gpztValue":"挂牌成功","hxs":0,"hxt":0,"hxw":0,"hyid":0,"hyjzsj":"","isnew":0,"jmlx":0,"jmqymc":"","jzmj":115.95,"lsbz":0,"mdmc":"杭州华玮房地产经纪有限公司","qycode":0,"qyid":0,"qyzt":0,"scgpshsj":"2022-07-05","sellnum":0,"sffzjg":0,"sjhm":"","sqhysj":"","szlc":"","szlcname":"","tjsum":0,"tygpbh":"38087141927","wtcsjg":600,"wtdqts":0,"wtxybh":"2022062209304952","wtxycode":0,"wtxyid":0,"xqid":0,"xqmc":"紫金港湾","xzqh":33,"xzqhname":"西湖区","zzcs":""},{"accountid":0,"accountname":"","cjsj":"2022-07-01","cqmc":"西湖区","cqsj":0,"cyrybh":"","czfs":0,"dqlc":"","fbzt":1,"fczsh":"杭房权证西移字第09670285号","fwcode":0,"fwtybh":"220701BP043388","fwyt":0,"fwytValue":"","gisx":"","gisy":"","gpfyid":3820433,"gpfyxzqh":0,"gphytgsj":"","gpid":569850605,"gplxfs":"","gplxrcode":0,"gplxrdh":"","gplxrxm":"卢传琴","gply":0,"gpzt":3,"gpztValue":"挂牌成功","hxs":0,"hxt":0,"hxw":0,"hyid":0,"hyjzsj":"","isnew":0,"jmlx":0,"jmqymc":"","jzmj":88.83,"lsbz":0,"mdmc":"杭州我爱我家房地产经纪有限公司保俶路分公司","qycode":0,"qyid":0,"qyzt":0,"scgpshsj":"2022-07-05","sellnum":0,"sffzjg":0,"sjhm":"","sqhysj":"","szlc":"","szlcname":"","tjsum":0,"tygpbh":"38204339333","wtcsjg":320,"wtdqts":0,"wtxybh":"2022070101520604","wtxycode":0,"wtxyid":0,"xqid":0,"xqmc":"金厦公寓","xzqh":33,"xzqhname":"西湖区","zzcs":""},{"accountid":0,"accountname":"","cjsj":"2022-07-03","cqmc":"西湖区","cqsj":0,"cyrybh":"","czfs":0,"dqlc":"","fbzt":1,"fczsh":"杭房权证西移字第10897627号","fwcode":0,"fwtybh":"220703YA224169","fwyt":0,"fwytValue":"","gisx":"","gisy":"","gpfyid":3822241,"gpfyxzqh":0,"gphytgsj":"","gpid":570667593,"gplxfs":"","gplxrcode":0,"gplxrdh":"","gplxrxm":"尹恩毅","gply":0,"gpzt":3,"gpztValue":"挂牌成功","hxs":0,"hxt":0,"hxw":0,"hyid":0,"hyjzsj":"","isnew":0,"jmlx":0,"jmqymc":"","jzmj":96.74,"lsbz":0,"mdmc":"杭州我爱我家房地产经纪有限公司保俶路分公司","qycode":0,"qyid":0,"qyzt":0,"scgpshsj":"2022-07-05","sellnum":0,"sffzjg":0,"sjhm":"","sqhysj":"","szlc":"","szlcname":"","tjsum":0,"tygpbh":"38222419191","wtcsjg":480,"wtdqts":0,"wtxybh":"2022070309237592","wtxycode":0,"wtxyid":0,"xqid":0,"xqmc":"紫金港湾","xzqh":33,"xzqhname":"西湖区","zzcs":""}],"totaltows":22776,"pageinfo":"<a href=\"javascript:void(0);\" class=\"c\" onclick=\"doPage(1);return false;\">首页</a><a href=\"javascript:void(0);\" class=\"c\" onclick=\"doPage(204);return false;\">上一页</a><a href=\"javascript:void(0);\" onclick=\"doPage(203);return false;\" class=\"c\" >203</a><a href=\"javascript:void(0);\" onclick=\"doPage(204);return false;\" class=\"c\" >204</a><a href=\"javascript:void(0);\" onclick=\"doPage(205);return false;\" class=\"d\" >205</a><a href=\"javascript:void(0);\" onclick=\"doPage(206);return false;\" class=\"c\" >206</a><a href=\"javascript:void(0);\" onclick=\"doPage(207);return false;\" class=\"c\" >207</a><a href=\"javascript:void(0)\" class=\"c\" onclick=\"doPage(206);return false;\">下一页</a><a href=\"javascript:void(0)\" class=\"c\" onclick=\"doPage(2278);return false;\">尾页</a><span class=\"nlc_totalpage\">共 <font class=\"color-blue09\">2278</font> 页 第<input type=\"text\" value=\"205\" name=\"_page\" id=\"_page\" onkeydown=\"javascript:if(event.keyCode==13)doPage($('#_page').val());\">页 <a href=\"javaScript:doPage($('#_page').val());\">确定</a></span><br/>(共22776条)"}