{"list":[{"accountid":0,"accountname":"","cjsj":"2021-05-11","cqmc":"西湖区","cqsj":0,"cyrybh":"","czfs":0,"dqlc":"","fbzt":1,"fczsh":"杭房权证西移字第15933363号","fwcode":0,"fwtybh":"190610842915","fwyt":0,"fwytValue":"","gisx":"","gisy":"","gpfyid":3393622,"gpfyxzqh":0,"gphytgsj":"","gpid":395870195,"gplxfs":"","gplxrcode":0,"gplxrdh":"","gplxrxm":"陈荣建","gply":0,"gpzt":3,"gpztValue":"挂牌成功","hxs":0,"hxt":0,"hxw":0,"hyid":0,"hyjzsj":"","isnew":0,"jmlx":0,"jmqymc":"","jzmj":86.98,"lsbz":0,"mdmc":"杭州我爱我家房地产经纪有限公司保俶路分公司","qycode":0,"qyid":0,"qyzt":0,"scgpshsj":"2021-05-12","sellnum":0,"sffzjg":0,"sjhm":"","sqhysj":"","szlc":"","szlcname":"","tjsum":0,"tygpbh":"33936223344","wtcsjg":610,"wtdqts":0,"wtxybh":"2021051102470194","wtxycode":0,"wtxyid":0,"xqid":0,"xqmc":"德雅公寓","xzqh":33,"xzqhname":"西湖区","zzcs":""},{"accountid":0,"accountname":"","cjsj":"2021-05-10","cqmc":"西湖区","cqsj":0,"cyrybh":"","czfs":0,"dqlc":"","fbzt":1,"fczsh":"杭房权证西移字第15089670号","fwcode":0,"fwtybh":"210410GW465471","fwyt":0,"fwytValue":"","gisx":"","gisy":"","gpfyid":3391926,"gpfyxzqh":0,"gphytgsj":"","gpid":395318160,"gplxfs":"","gplxrcode":0,"gplxrdh":"","gplxrxm":"胡伟成","gply":0,"gpzt":3,"gpztValue":"挂牌成功","hxs":0,"hxt":0,"hxw":0,"hyid":0,"hyjzsj":"","isnew":0,"jmlx":0,"jmqymc":"","jzmj":76.11,"lsbz":0,"mdmc":"杭州豪世华邦文教房地产代理有限公司","qycode":0,"qyid":0,"qyzt":0,"scgpshsj":"2021-05-12","sellnum":0,"sffzjg":0,"sjhm":"","sqhysj":"","szlc":"","szlcname":"","tjsum":0,"tygpbh":"33919261323","wtcsjg":890,"wtdqts":0,"wtxybh":"2021051009018159","wtxycode":0,"wtxyid":0,"xqid":0,"xqmc":"西溪河东","xzqh":33,"xzqhname":"西湖区","zzcs":""},{"accountid":0,"accountname":"","cjsj":"2021-04-27","cqmc":"西湖区","cqsj":0,"cyrybh":"","czfs":0,"dqlc":"","fbzt":1,"fczsh":"浙(2018)杭州市不动产权第0201516号","fwcode":0,"fwtybh":"181118504791","fwyt":0,"fwytValue":"","gisx":"","gisy":"","gpfyid":3378097,"gpfyxzqh":0,"gphytgsj":"","gpid":389530199,"gplxfs":"","gplxrcode":0,"gplxrdh":"","gplxrxm":"周健枫","gply":0,"gpzt":3,"gpztValue":"挂牌成功","hxs":0,"hxt":0,"hxw":0,"hyid":0,"hyjzsj":"","isnew":0,"jmlx":0,"jmqymc":"","jzmj":65.19,"lsbz":0,"mdmc":"浙江链家房地产经纪有限公司杭州转塘文景路店","qycode":0,"qyid":0,"qyzt":0,"scgpshsj":"2021-05-12","sellnum":0,"sffzjg":0,"sjhm":"","sqhysj":"","szlc":"","szlcname":"","tjsum":0,"tygpbh":"33780975411","wtcsjg":115,"wtdqts":0,"wtxybh":"2021042711420198","wtxycode":0,"wtxyid":0,"xqid":0,"xqmc":"钱江浮山商业中心","xzqh":33,"xzqhname":"西湖区","zzcs":""},{"accountid":0,"accountname":"","cjsj":"2021-05-10","cqmc":"西湖区","cqsj":0,"cyrybh":"","czfs":0,"dqlc":"","fbzt":1,"fczsh":"杭房权证西移字第12078853号","fwcode":0,"fwtybh":"170816496198","fwyt":0,"fwytValue":"","gisx":"","gisy":"","gpfyid":3392193,"gpfyxzqh":0,"gphytgsj":"","gpid":395377508,"gplxfs":"","gplxrcode":0,"gplxrdh":"","gplxrxm":"安洋洋","gply":0,"gpzt":3,"gpztValue":"挂牌成功","hxs":0,"hxt":0,"hxw":0,"hyid":0,"hyjzsj":"","isnew":0,"jmlx":0,"jmqymc":"","jzmj":87.87,"lsbz":0,"mdmc":"浙江链家房地产经纪有限公司杭州文一路九店","qycode":0,"qyid":0,"qyzt":0,"scgpshsj":"2021-05-12","sellnum":0,"sffzjg":0,"sjhm":"","sqhysj":"","szlc":"","szlcname":"","tjsum":0,"tygpbh":"33921936461","wtcsjg":398,"wtdqts":0,"wtxybh":"2021051010497507","wtxycode":0,"wtxyid":0,"xqid":0,"xqmc":"天苑花园","xzqh":33,"xzqhname":"西湖区","zzcs":""},{"accountid":0,"accountname":"","cjsj":"2021-05-11","cqmc":"西湖区","cqsj":0,"cyrybh":"","czfs":0,"dqlc":"","fbzt":1,"fczsh":"杭房权证拱改字第08333024号","fwcode":0,"fwtybh":"190502271866","fwyt":0,"fwytValue":"","gisx":"","gisy":"","gpfyid":3393009,"gpfyxzqh":0,"gphytgsj":"","gpid":395743290,"gplxfs":"","gplxrcode":0,"gplxrdh":"","gplxrxm":"储诚俊","gply":0,"gpzt":3,"gpztValue":"挂牌成功","hxs":0,"hxt":0,"hxw":0,"hyid":0,"hyjzsj":"","isnew":0,"jmlx":0,"jmqymc":"","jzmj":95.89,"lsbz":0,"mdmc":"杭州我爱我家房地产经纪有限公司保俶路分公司","qycode":0,"qyid":0,"qyzt":0,"scgpshsj":"2021-05-12","sellnum":0,"sffzjg":0,"sjhm":"","sqhysj":"","szlc":"","szlcname":"","tjsum":0,"tygpbh":"33930092658","wtcsjg":325,"wtdqts":0,"wtxybh":"2021051107533289","wtxycode":0,"wtxyid":0,"xqid":0,"xqmc":"祥符路","xzqh":33,"xzqhname":"西湖区","zzcs":""},{"accountid":0,"accountname":"","cjsj":"2021-05-10","cqmc":"西湖区","cqsj":0,"cyrybh":"","czfs":0,"dqlc":"","fbzt":1,"fczsh":"杭房权证西移字第09703042号","fwcode":0,"fwtybh":"210510MX216517","fwyt":0,"fwytValue":"","gisx":"","gisy":"","gpfyid":3392165,"gpfyxzqh":0,"gphytgsj":"","gpid":395365229,"gplxfs":"","gplxrcode":0,"gplxrdh":"","gplxrxm":"宋林","gply":0,"gpzt":3,"gpztValue":"挂牌成功","hxs":0,"hxt":0,"hxw":0,"hyid":0,"hyjzsj":"","isnew":0,"jmlx":0,"jmqymc":"","jzmj":80.96,"lsbz":0,"mdmc":"杭州中盟房地产经纪有限公司","qycode":0,"qyid":0,"qyzt":0,"scgpshsj":"2021-05-12","sellnum":0,"sffzjg":0,"sjhm":"","sqhysj":"","szlc":"","szlcname":"","tjsum":0,"tygpbh":"33921651722","wtcsjg":345,"wtdqts":0,"wtxybh":"2021051010385228","wtxycode":0,"wtxyid":0,"xqid":0,"xqmc":"金厦公寓","xzqh":33,"xzqhname":"西湖区","zzcs":""},{"accountid":0,"accountname":"","cjsj":"2021-05-09","cqmc":"西湖区","cqsj":0,"cyrybh":"","czfs":0,"dqlc":"","fbzt":1,"fczsh":"杭房权证西换字第0114451号","fwcode":0,"fwtybh":"210508BU044111","fwyt":0,"fwytValue":"","gisx":"","gisy":"","gpfyid":3390503,"gpfyxzqh":0,"gphytgsj":"","gpid":394898826,"gplxfs":"","gplxrcode":0,"gplxrdh":"","gplxrxm":"曹晨晨","gply":0,"gpzt":3,"gpztValue":"挂牌成功","hxs":0,"hxt":0,"hxw":0,"hyid":0,"hyjzsj":"","isnew":0,"jmlx":0,"jmqymc":"","jzmj":50.09,"lsbz":0,"mdmc":"浙江链家房地产经纪有限公司杭州莫干山路店","qycode":0,"qyid":0,"qyzt":0,"scgpshsj":"2021-05-12","sellnum":0,"sffzjg":0,"sjhm":"","sqhysj":"","szlc":"","szlcname":"","tjsum":0,"tygpbh":"33905032212","wtcsjg":440,"wtdqts":0,"wtxybh":"2021050908198825","wtxycode":0,"wtxyid":0,"xqid":0,"xqmc":"白荡海人家","xzqh":33,"xzqhname":"西湖区","zzcs":""},{"accountid":0,"accountname":"","cjsj":"2021-05-11","cqmc":"西湖区","cqsj":0,"cyrybh":"","czfs":0,"dqlc":"","fbzt":1,"fczsh":"杭房权证西移字第13595141号","fwcode":0,"fwtybh":"210320BZ532756","fwyt":0,"fwytValue":"","gisx":"","gisy":"","gpfyid":3393049,"gpfyxzqh":0,"gphytgsj":"","gpid":395750238,"gplxfs":"","gplxrcode":0,"gplxrdh":"","gplxrxm":"卢早霞","gply":0,"gpzt":3,"gpztValue":"挂牌成功","hxs":0,"hxt":0,"hxw":0,"hyid":0,"hyjzsj":"","isnew":0,"jmlx":0,"jmqymc":"","jzmj":96.96,"lsbz":0,"mdmc":"杭州我爱我家房地产经纪有限公司保俶路分公司","qycode":0,"qyid":0,"qyzt":0,"scgpshsj":"2021-05-12","sellnum":0,"sffzjg":0,"sjhm":"","sqhysj":"","szlc":"","szlcname":"","tjsum":0,"tygpbh":"33930492447","wtcsjg":468,"wtdqts":0,"wtxybh":"2021051108320237","wtxycode":0,"wtxyid":0,"xqid":0,"xqmc":"颐景园","xzqh":33,"xzqhname":"西湖区","zzcs":""},{"accountid":0,"accountname":"","cjsj":"2021-05-10","cqmc":"西湖区","cqsj":0,"cyrybh":"","czfs":0,"dqlc":"","fbzt":1,"fczsh":"杭房权证西移字第13576315号","fwcode":0,"fwtybh":"191126728630","fwyt":0,"fwytValue":"","gisx":"","gisy":"","gpfyid":3392942,"gpfyxzqh":0,"gphytgsj":"","gpid":395643653,"gplxfs":"","gplxrcode":0,"gplxrdh":"","gplxrxm":"刘朋礼","gply":0,"gpzt":3,"gpztValue":"挂牌成功","hxs":0,"hxt":0,"hxw":0,"hyid":0,"hyjzsj":"","isnew":0,"jmlx":0,"jmqymc":"","jzmj":42.29,"lsbz":0,"mdmc":"杭州我爱我家房地产经纪有限公司保俶路分公司","qycode":0,"qyid":0,"qyzt":0,"scgpshsj":"2021-05-12","sellnum":0,"sffzjg":0,"sjhm":"","sqhysj":"","szlc":"","szlcname":"","tjsum":0,"tygpbh":"33929426924","wtcsjg":410,"wtdqts":0,"wtxybh":"2021051007183652","wtxycode":0,"wtxyid":0,"xqid":0,"xqmc":"曙光新村","xzqh":33,"xzqhname":"西湖区","zzcs":""},{"accountid":0,"accountname":"","cjsj":"2021-05-10","cqmc":"西湖区","cqsj":0,"cyrybh":"","czfs":0,"dqlc":"","fbzt":1,"fczsh":"浙(2019)杭州市不动产权第0061136号","fwcode":0,"fwtybh":"180801830064","fwyt":0,"fwytValue":"","gisx":"","gisy":"","gpfyid":3392954,"gpfyxzqh":0,"gphytgsj":"","gpid":395648770,"gplxfs":"","gplxrcode":0,"gplxrdh":"","gplxrxm":"曹皖豫","gply":0,"gpzt":3,"gpztValue":"挂牌成功","hxs":0,"hxt":0,"hxw":0,"hyid":0,"hyjzsj":"","isnew":0,"jmlx":0,"jmqymc":"","jzmj":50.61,"lsbz":0,"mdmc":"杭州我爱我家房地产经纪有限公司保俶路分公司","qycode":0,"qyid":0,"qyzt":0,"scgpshsj":"2021-05-11","sellnum":0,"sffzjg":0,"sjhm":"","sqhysj":"","szlc":"","szlcname":"","tjsum":0,"tygpbh":"33929547326","wtcsjg":500,"wtdqts":0,"wtxybh":"2021051008178769","wtxycode":0,"wtxyid":0,"xqid":0,"xqmc":"石灰桥新村","xzqh":33,"xzqhname":"西湖区","zzcs":""}],"totaltows":22776,"pageinfo":"<a href=\"javascript:void(0);\" class=\"c\" onclick=\"doPage(1);return false;\">首页</a><a href=\"javascript:void(0);\" class=\"c\" onclick=\"doPage(1577);return false;\">上一页</a><a href=\"javascript:void(0);\" onclick=\"doPage(1576);return false;\" class=\"c\" >1576</a><a href=\"javascript:void(0);\" onclick=\"doPage(1577);return false;\" class=\"c\" >1577</a><a href=\"javascript:void(0);\" onclick=\"doPage(1578);return false;\" class=\"d\" >1578</a><a href=\"javascript:void(0);\" onclick=\"doPage(1579);return false;\" class=\"c\" >1579</a><a href=\"javascript:void(0);\" onclick=\"doPage(1580);return false;\" class=\"c\" >1580</a><a href=\"javascript:void(0)\" class=\"c\" onclick=\"doPage(1579);return false;\">下一页</a><a href=\"javascript:void(0)\" class=\"c\" onclick=\"doPage(2278);return false;\">尾页</a><span class=\"nlc_totalpage\">共 <font class=\"color-blue09\">2278</font> 页 第<input type=\"text\" value=\"1578\" name=\"_page\" id=\"_page\" onkeydown=\"javascript:if(event.keyCode==13)doPage($('#_page').val());\">页 <a href=\"javaScript:doPage($('#_page').val());\">确定</a></span><br/>(共22776条)"}