{"date":"2024-01-14","patch":true,"availableHouse":[],"commercialHouse":[["上城","4套","595.92m²","2套","235.67m²"],["拱墅","6套","1288.79m²","2套","275.71m²"],["西湖","0套","0m²","0套","0m²"],["滨江","8套","959.1m²","8套","959.1m²"],["萧山","0套","0m²","0套","0m²"],["余杭","13套","1749.06m²","13套","1749.06m²"],["临平","17套","2341.89m²","12套","2163.34m²"],["钱塘","3套","289.49m²","3套","286.49m²"],["富阳","1套","108.57m²","1套","108.57m²"],["临安","7套","897.21m²","7套","897.21m²"],["桐庐","0套","0m²","0套","0m²"],["淳安","7套","681.53m²","7套","681.53m²"],["建德","0套","0m²","0套","0m²"],["合计","66套","8911.56m²","55套","7356.68m²"]],"previouslyOwnedHouse":[["上城","35套","3009m²","35套","3009m²"],["拱墅","34套","2905.39m²","33套","2855m²"],["西湖","27套","2300.07m²","25套","2214.9m²"],["滨江","13套","1313.87m²","13套","1313.87m²"],["萧山","0套","0m²","0套","0m²"],["余杭","26套","2656.03m²","24套","2583.4m²"],["临平","20套","2118.1m²","20套","2118.1m²"],["钱塘","5套","475.03m²","5套","475.03m²"],["富阳","0套","0m²","0套","0m²"],["临安","0套","0m²","0套","0m²"],["桐庐","0套","0m²","0套","0m²"],["淳安","0套","0m²","0套","0m²"],["建德","0套","0m²","0套","0m²"],["合计","160套","14777.49m²","155套","14569.3m²"]]}