{"date":"2023-08-11","patch":true,"availableHouse":[],"commercialHouse":[["上城","10套","1122.64m²","9套","1081.57m²"],["拱墅","8套","1614.61m²","3套","490.13m²"],["西湖","2套","439.49m²","1套","138.39m²"],["滨江","0套","0m²","0套","0m²"],["萧山","35套","4326.15m²","29套","3496.19m²"],["余杭","20套","2750.43m²","19套","2691.56m²"],["临平","20套","2110.39m²","17套","1685.15m²"],["钱塘","7套","958.78m²","7套","958.78m²"],["富阳","20套","2191.07m²","20套","2191.07m²"],["临安","3套","420.39m²","3套","420.39m²"],["桐庐","7套","754.32m²","4套","408.45m²"],["淳安","2套","197.48m²","2套","197.48m²"],["建德","2套","252.53m²","2套","252.53m²"],["合计","136套","17138.28m²","116套","14011.69m²"]],"previouslyOwnedHouse":[["上城","16套","1474.44m²","16套","1474.44m²"],["拱墅","20套","1607m²","17套","1455.84m²"],["西湖","15套","1602.37m²","12套","1217.77m²"],["滨江","2套","139.72m²","2套","139.72m²"],["萧山","15套","1693.26m²","14套","1642.32m²"],["余杭","20套","2192.1m²","19套","2085.45m²"],["临平","22套","2373.59m²","18套","2203.77m²"],["钱塘","9套","1084.89m²","9套","1084.89m²"],["富阳","7套","1133.45m²","7套","1133.45m²"],["临安","10套","1061.83m²","10套","1061.83m²"],["桐庐","4套","267.59m²","3套","233.47m²"],["淳安","3套","220.22m²","2套","124.7m²"],["建德","8套","1054.46m²","8套","1054.46m²"],["合计","151套","15904.92m²","137套","14912.11m²"]]}